structurizr2csv/__init__.py
structurizr2csv/convert.py
structurizr2csv/coordinates.py
structurizr2csv/dsl2json.py
structurizr2csv/enums.py
structurizr2csv/settings.py
structurizr2csv/style.py
structurizr2csv/utils.py
structurizr2csv/workspace.py
structurizr2csv/workspace_extension.py
structurizr2csv/elements/__init__.py
structurizr2csv/elements/base_box.py
structurizr2csv/elements/bounding_box.py
structurizr2csv/elements/box.py
structurizr2csv/elements/connector.py
structurizr2csv/elements/diagram.py
structurizr2csv/elements/group.py
structurizr2csv/elements/legend.py
structurizr2csv/elements/title.py
structurizr2csv/labels/box.txt
structurizr2csv/labels/group_1.txt
structurizr2csv/labels/group_2.txt
structurizr2csv/labels/legend_header.txt
structurizr2csv/labels/legend_row.txt
structurizr2csv/labels/title.txt
structurizr2csv/styles/component.txt
structurizr2csv/styles/connector.txt
structurizr2csv/styles/container.txt
structurizr2csv/styles/cylinder.txt
structurizr2csv/styles/group_1.txt
structurizr2csv/styles/group_2.txt
structurizr2csv/styles/hexagon.txt
structurizr2csv/styles/legend_header.txt
structurizr2csv/styles/legend_row.txt
structurizr2csv/styles/person.txt
structurizr2csv/styles/pipe.txt
structurizr2csv/styles/softwareSystem.txt
structurizr2csv/styles/styles.txt
structurizr2csv/styles/title.txt
structurizr2csv/styles/web-browser.txt
structurizr2csv-0.1.dist-info/LICENSE
structurizr2csv-0.1.dist-info/METADATA
structurizr2csv-0.1.dist-info/WHEEL
structurizr2csv-0.1.dist-info/entry_points.txt
structurizr2csv-0.1.dist-info/top_level.txt
structurizr2csv-0.1.dist-info/RECORD
