Metadata-Version: 2.1
Name: structurizr2csv
Version: 0.1
Summary: Convert structurizr DSL or JSON (for describing C4 models) to diagrams.net CSV format
Home-page: https://gitlab.com/souliane/structurizr2csv
Author: Adrien Cossa
Author-email: souliane@mailoo.org
License: BSD-3-Clause
Project-URL: Source, https://gitlab.com/souliane/structurizr2csv
Project-URL: Documentation, https://gitlab.com/souliane/structurizr2csv
Platform: UNKNOWN
Classifier: Development Status :: 4 - Beta
Classifier: Environment :: Console
Classifier: Intended Audience :: Developers
Classifier: Intended Audience :: Education
Classifier: Intended Audience :: Information Technology
Classifier: License :: OSI Approved :: BSD License
Classifier: Operating System :: OS Independent
Classifier: Programming Language :: Python
Classifier: Programming Language :: Python :: 3
Classifier: Programming Language :: Python :: 3.10
Classifier: Topic :: Software Development :: Documentation
Classifier: Topic :: Scientific/Engineering :: Visualization
Requires-Python: >=3.10
License-File: LICENSE
Requires-Dist: pydantic (==1.8.2)
